question_generation/__init__.py
question_generation/run_qa.py
question_generation/run_qg.py
question_generation/train_qa.py
question_generation/pipelines/__init__.py
question_generation/pipelines/question_answering.py
question_generation/pipelines/question_generation.py
question_generation/pipelines/utils_qa.py
question_generation-1.0.5.dist-info/LICENSE
question_generation-1.0.5.dist-info/METADATA
question_generation-1.0.5.dist-info/WHEEL
question_generation-1.0.5.dist-info/top_level.txt
question_generation-1.0.5.dist-info/RECORD
