Metadata-Version: 2.1
Name: question-generation
Version: 1.0.5
Summary: Question Generation and Question Answering Pipeline
Home-page: https://github.com/algolet/question_generation
Author: algolet
Author-email: wei.cai@algolet.com
License: Apache
Platform: UNKNOWN
Classifier: Intended Audience :: Developers
Classifier: Intended Audience :: Education
Classifier: Intended Audience :: Science/Research
Classifier: License :: OSI Approved :: Apache Software License
Classifier: Programming Language :: Python :: 3
Classifier: Programming Language :: Python :: 3.6
Classifier: Programming Language :: Python :: 3.7
Classifier: Programming Language :: Python :: 3.8
Classifier: Programming Language :: Python :: 3.9
Classifier: Topic :: Scientific/Engineering :: Artificial Intelligence
Requires-Python: >=3.6.0
Requires-Dist: transformers (>=4.12.5)
Requires-Dist: datasets (>=1.15.1)
Requires-Dist: torch (>=1.3)
